AUTHORS.rst
CONTRIBUTING.rst
HISTORY.rst
LICENSE
MANIFEST.in
README.rst
setup.cfg
setup.py
c3dp/COnversion_MCSTAStoMCVINE_file.py
c3dp/DAC_geo.py
c3dp/Diffraction_peaks.py
c3dp/EventMonitor_4D.py
c3dp/Peak_Detection.py
c3dp/__init__.py
c3dp/c3dp.py
c3dp/cad.py
c3dp/clampcell_geo.py
c3dp/collimator_geometry.py
c3dp/collimator_support.py
c3dp/collimator_zigzagBlade.py
c3dp/conf.py
c3dp/convert2nxs.py
c3dp/create_collimator_geometry.py
c3dp/detector.py
c3dp/from_d_toTOF.py
c3dp/gauge_volume.py
c3dp/gauge_volume_allchannels.py
c3dp/masking_nexus_givenKernel.py
c3dp/myinstrument.py
c3dp/myinstrument_events.py
c3dp/neutrons2Id.py
c3dp/optimization.py
c3dp/plot_all_reduction_own.py
c3dp/reduce_nexasdata_using_mantid.py
c3dp/reduction.py
c3dp/rotate_detector_for_reduction_mantid.py
c3dp/sampleassembly_program.py
c3dp/support_only_for_collimator.py
c3dp.egg-info/PKG-INFO
c3dp.egg-info/SOURCES.txt
c3dp.egg-info/dependency_links.txt
c3dp.egg-info/not-zip-safe
c3dp.egg-info/requires.txt
c3dp.egg-info/top_level.txt
docs/Makefile
docs/authors.rst
docs/conf.py
docs/contributing.rst
docs/history.rst
docs/index.rst
docs/installation.rst
docs/make.bat
docs/readme.rst
docs/usage.rst
docs/_build/html/_static/ajax-loader.gif
docs/_build/html/_static/comment-bright.png
docs/_build/html/_static/comment-close.png
docs/_build/html/_static/comment.png
docs/_build/html/_static/down-pressed.png
docs/_build/html/_static/down.png
docs/_build/html/_static/file.png
docs/_build/html/_static/minus.png
docs/_build/html/_static/plus.png
docs/_build/html/_static/up-pressed.png
docs/_build/html/_static/up.png
tests/_test_gauge_volume.py
tests/create_Multiple_Collimators.py
tests/mcvine_run_script_kwds.yml
tests/test_c3dp.py
tests/test_convert2nxs.py
tests/test_gauge_volume.py
tests/test_masking.py
tests/test_reduce_mantid.py
tests/test_run_collimator.py