Metadata-Version: 1.1
Name: c3dp
Version: 0.1.0
Summary: design of 3D printed high pressure cell collimator
Home-page: https://github.com/fahima-islam/c3dp
Author: Fahima islam
Author-email: ffiqnf.2017@gmail.com
License: MIT license
Download-URL: https://github.com/Fahima-Islam/c3dp/archive/v0.1.0.tar.gz
Keywords: c3dp
Platform: UNKNOWN
Classifier: Development Status :: 2 - Pre-Alpha
Classifier: Intended Audience :: Developers
Classifier: License :: OSI Approved :: MIT License
Classifier: Natural Language :: English
Classifier: Programming Language :: Python :: 2
Classifier: Programming Language :: Python :: 2.7
Classifier: Programming Language :: Python :: 3
Classifier: Programming Language :: Python :: 3.4
Classifier: Programming Language :: Python :: 3.5
Classifier: Programming Language :: Python :: 3.6
Classifier: Programming Language :: Python :: 3.7
